{
  "function_name": "ag6xx_setup",
  "end_flag": false,
  "functionality_list": [],
  "is_update": true,
  "purity": "low",
  "callee_func_info_list": [
    {
      "callee_function_name": "release_firmware",
      "get_or_put": "put",
      "index": 1,
      "location": "parameter",
      "member_access_path": "fw.priv.ref.refcount",
      "member_type_chain": "firmware--fw_priv--kref--refcount_t"
    },
    {
      "callee_function_name": "kfree_skb",
      "get_or_put": "put",
      "index": "1",
      "location": "parameter",
      "member_access_path": "skb.users.refs",
      "member_type_chain": "sk_buff--refcount_t--atomic_t"
    }
  ],
  "analyzed_callee_snapshot": [
    {
      "callee_function_name": "release_firmware",
      "get_or_put": "put",
      "index": 1,
      "location": "parameter",
      "member_access_path": "fw.priv.ref.refcount",
      "member_type_chain": "firmware--fw_priv--kref--refcount_t"
    },
    {
      "callee_function_name": "kfree_skb",
      "get_or_put": "put",
      "index": "1",
      "location": "parameter",
      "member_access_path": "skb.users.refs",
      "member_type_chain": "sk_buff--refcount_t--atomic_t"
    }
  ],
  "conditionality": "unconditional",
  "must_check": false,
  "retry_on_failure": false,
  "retry_reason": "Not a wrapper — refcount operations are incidental; retry logic is not relevant.",
  "contract_summary": "",
  "stages": {
    "judge": {
      "need_more_info": false,
      "is_wrapper": false,
      "passes_critical_variable": false,
      "purity": "low",
      "reason": "The function's primary purpose is hardware setup and firmware loading for an Intel Bluetooth controller. It performs extensive device-specific operations (entering manufacturing mode, reading version, checking platform/variant, loading bddata and patch firmware, applying patches, exiting manufacturing mode, setting event mask, checking bdaddr). The reference-count operations (request_firmware/release_firmware, kfree_skb) are incidental steps within the broader initialization logic, not the core purpose. The function does not acquire or release a reference for an object that it passes to the caller or returns.",
      "conditionality": "unconditional",
      "must_check": false,
      "retry_on_failure": false,
      "retry_reason": "Not a wrapper — refcount operations are incidental; retry logic is not relevant.",
      "contract_summary": ""
    }
  },
  "final": {
    "status": "ok",
    "is_wrapper": false,
    "purity": "low",
    "functionality_list": [],
    "callee_count": 2,
    "conditionality": "unconditional",
    "must_check": false,
    "retry_on_failure": false,
    "retry_reason": "Not a wrapper — refcount operations are incidental; retry logic is not relevant.",
    "contract_summary": ""
  }
}