{
  "function_name": "br_vlan_add",
  "end_flag": false,
  "functionality_list": [],
  "is_update": true,
  "purity": "low",
  "callee_func_info_list": [
    {
      "callee_function_name": "refcount_set",
      "get_or_put": "set",
      "index": "1",
      "location": "parameter",
      "member_access_path": "r.refs",
      "member_type_chain": "refcount_t--atomic_t"
    }
  ],
  "analyzed_callee_snapshot": [
    {
      "callee_function_name": "refcount_set",
      "get_or_put": "set",
      "index": "1",
      "location": "parameter",
      "member_access_path": "r.refs",
      "member_type_chain": "refcount_t--atomic_t"
    }
  ],
  "conditionality": "conditional_on_path",
  "must_check": false,
  "retry_on_failure": false,
  "retry_reason": "Not applicable - not a wrapper.",
  "contract_summary": "",
  "stages": {
    "judge": {
      "need_more_info": false,
      "is_wrapper": false,
      "passes_critical_variable": false,
      "purity": "low",
      "reason": "The primary purpose is to add a VLAN to the bridge (allocation, initialization, flag handling, and calling __vlan_add). The refcount_set/br_vlan_add_existing calls are one part of broader business logic, not the main focus. The function does not pass a reference-counted object to the caller for management; the VLAN is added to the bridge tree.",
      "conditionality": "conditional_on_path",
      "must_check": false,
      "retry_on_failure": false,
      "retry_reason": "Not applicable - not a wrapper.",
      "contract_summary": ""
    }
  },
  "final": {
    "status": "ok",
    "is_wrapper": false,
    "purity": "low",
    "functionality_list": [],
    "callee_count": 1,
    "conditionality": "conditional_on_path",
    "must_check": false,
    "retry_on_failure": false,
    "retry_reason": "Not applicable - not a wrapper.",
    "contract_summary": ""
  }
}